setup.py
httpx/__init__.py
httpx/__version__.py
httpx/_api.py
httpx/_auth.py
httpx/_client.py
httpx/_compat.py
httpx/_config.py
httpx/_content.py
httpx/_decoders.py
httpx/_exceptions.py
httpx/_main.py
httpx/_models.py
httpx/_multipart.py
httpx/_status_codes.py
httpx/_types.py
httpx/_urlparse.py
httpx/_urls.py
httpx/_utils.py
httpx/call.py
httpx_upgrade.egg-info/PKG-INFO
httpx_upgrade.egg-info/SOURCES.txt
httpx_upgrade.egg-info/dependency_links.txt
httpx_upgrade.egg-info/requires.txt
httpx_upgrade.egg-info/top_level.txt