Metadata-Version: 2.1
Name: httpx-upgrade
Version: 0.0.1
Summary: httpx-upgrade
Author: httpx-upgrade
